senkawa/__init__.py
senkawa/brace_expand.py
senkawa/errors.py
senkawa/expressions.py
senkawa/glob.py
senkawa-0.1.0.dist-info/LICENSE
senkawa-0.1.0.dist-info/METADATA
senkawa-0.1.0.dist-info/WHEEL
senkawa-0.1.0.dist-info/RECORD
