Metadata-Version: 2.1
Name: senkawa
Version: 0.1.0
Summary: Glob with Bash-style brache expansion
License: MIT
Author: Manabu Niseki
Author-email: manabu.niseki@gmail.com
Requires-Python: >=3.10,<4.0
Classifier: License :: OSI Approved :: MIT License
Classifier: Programming Language :: Python :: 3
Classifier: Programming Language :: Python :: 3.10
Classifier: Programming Language :: Python :: 3.11
Classifier: Programming Language :: Python :: 3.12
Requires-Dist: pyparsing (>=3.1,<4.0)
